entity_addict/__init__.py
entity_addict/__version__.py
entity_addict/entity.py
entity_addict/test/__init__.py
entity_addict/test/test_entity.py
entity_addict-1.2.1.dist-info/LICENSE
entity_addict-1.2.1.dist-info/WHEEL
entity_addict-1.2.1.dist-info/METADATA
entity_addict-1.2.1.dist-info/RECORD
